[
    {
        "Plan": {
            "Node Type": "Other",
            "Node Type ID": "42",
            "Total Cost": 306048.700292,
            "Plan Rows": 1.0,
            "Plans": [
                {
                    "Node Type": "Other",
                    "Node Type ID": "45",
                    "Total Cost": 306048.685292,
                    "Plan Rows": 2.0,
                    "Plans": [
                        {
                            "Node Type": "Other",
                            "Node Type ID": "42",
                            "Total Cost": 305048.485292,
                            "Plan Rows": 1.0,
                            "Plans": [
                                {
                                    "Node Type": "Hash Join",
                                    "Node Type ID": "38",
                                    "Total Cost": 304616.510292,
                                    "Plan Rows": 172786.0,
                                    "Plans": [
                                        {
                                            "Node Type": "Seq Scan",
                                            "Node Type ID": "19",
                                            "Relation Name": "movie_info",
                                            "Total Cost": 239478.104167,
                                            "Plan Rows": 870519.0
                                        },
                                        {
                                            "Node Type": "Other",
                                            "Node Type ID": "47",
                                            "Total Cost": 51803.05625,
                                            "Plan Rows": 209139.0,
                                            "Plans": [
                                                {
                                                    "Node Type": "Seq Scan",
                                                    "Node Type ID": "19",
                                                    "Relation Name": "title",
                                                    "Total Cost": 51803.05625,
                                                    "Plan Rows": 209139.0
                                                }
                                            ]
                                        }
                                    ]
                                }
                            ]
                        }
                    ]
                }
            ]
        }
    }
]